spacy_coptic/__init__.py
spacy_coptic/coptic.py
spacy_coptic-0.8.1.dist-info/LICENSE.txt
spacy_coptic-0.8.1.dist-info/METADATA
spacy_coptic-0.8.1.dist-info/WHEEL
spacy_coptic-0.8.1.dist-info/top_level.txt
spacy_coptic-0.8.1.dist-info/RECORD
