Metadata-Version: 2.1
Name: spacy-coptic
Version: 0.8.1
Summary: Coptic NLP wrapper for spaCy
Home-page: https://github.com/KoichiYasuoka/spaCy-Coptic
Author: Koichi Yasuoka
Author-email: yasuoka@kanji.zinbun.kyoto-u.ac.jp
License: MIT
Project-URL: coptic-nlp, https://github.com/CopticScriptorium/coptic-nlp
Project-URL: Source, https://github.com/KoichiYasuoka/spaCy-Coptic
Project-URL: Tracker, https://github.com/KoichiYasuoka/spaCy-Coptic/issues
Keywords: Coptic spaCy
Classifier: License :: OSI Approved :: MIT License
Classifier: Programming Language :: Python :: 3
Classifier: Operating System :: POSIX :: Linux
Classifier: Topic :: Text Processing :: Linguistic
Requires-Python: >=3.6
License-File: LICENSE.txt
Requires-Dist: deplacy (>=2.1.0)
Requires-Dist: spacy (>=2.2.2)
